hcsegment/__init__.py
hcsegment/cli.py
hcsegment/run_denoise.py
hcsegment/run_mask_neurites.py
hcsegment/run_mask_nuclei.py
hcsegment/run_stitch.py
hcsegment/modules/denoise.py
hcsegment/modules/image_stitch.py
hcsegment/modules/io_utils.py
hcsegment/modules/neurite_segment.py
hcsegment/modules/normalizations.py
hcsegment/modules/nuclei_segment.py
hcsegment-0.0.8.dist-info/METADATA
hcsegment-0.0.8.dist-info/WHEEL
hcsegment-0.0.8.dist-info/entry_points.txt
hcsegment-0.0.8.dist-info/top_level.txt
hcsegment-0.0.8.dist-info/RECORD
