Metadata-Version: 2.4
Name: hcsegment
Version: 0.0.8
Summary: Cell segmentation from HCS images
Author: Chris Viets
Project-URL: Homepage, https://github.com/cviets/hcsegment
Project-URL: Bug Tracker, https://github.com/cviets/hcsegment/issues
Requires-Python: >=3.6
Requires-Dist: numpy
Requires-Dist: iohub
Requires-Dist: tifffile
Requires-Dist: scipy
Requires-Dist: scikit-image
Requires-Dist: matplotlib
